corefoundationasyncio/__init__.py
corefoundationasyncio/eventloop.py
mpd_now_playable-1.5.4.dist-info/METADATA
mpd_now_playable-1.5.4.dist-info/WHEEL
mpd_now_playable-1.5.4.dist-info/entry_points.txt
mpd_now_playable/__init__.py
mpd_now_playable/__version__.py
mpd_now_playable/cache.py
mpd_now_playable/cli.py
mpd_now_playable/config/__init__.py
mpd_now_playable/config/load.py
mpd_now_playable/config/model.py
mpd_now_playable/config/schema.py
mpd_now_playable/mpd/__init__.py
mpd_now_playable/mpd/artwork_cache.py
mpd_now_playable/mpd/command/__init__.py
mpd_now_playable/mpd/command/model.py
mpd_now_playable/mpd/command/playback.py
mpd_now_playable/mpd/command/queue.py
mpd_now_playable/mpd/command/settings.py
mpd_now_playable/mpd/command/types/__init__.py
mpd_now_playable/mpd/command/types/command.py
mpd_now_playable/mpd/command/types/relative.py
mpd_now_playable/mpd/convert/__init__.py
mpd_now_playable/mpd/convert/to_playback.py
mpd_now_playable/mpd/convert/to_song.py
mpd_now_playable/mpd/listener.py
mpd_now_playable/mpd/logo.svg
mpd_now_playable/mpd/types.py
mpd_now_playable/playback/__init__.py
mpd_now_playable/playback/playback.py
mpd_now_playable/playback/queue.py
mpd_now_playable/playback/settings.py
mpd_now_playable/playback/state.py
mpd_now_playable/player.py
mpd_now_playable/py.typed
mpd_now_playable/receivers/__init__.py
mpd_now_playable/receivers/cocoa/__init__.py
mpd_now_playable/receivers/cocoa/convert/__init__.py
mpd_now_playable/receivers/cocoa/convert/playback_to_media_item.py
mpd_now_playable/receivers/cocoa/convert/settings_to_cocoa.py
mpd_now_playable/receivers/cocoa/convert/song_to_media_item.py
mpd_now_playable/receivers/cocoa/convert/to_nsimage.py
mpd_now_playable/receivers/cocoa/convert/to_state.py
mpd_now_playable/receivers/cocoa/now_playing.py
mpd_now_playable/receivers/cocoa/persistent_id.py
mpd_now_playable/receivers/websockets/__init__.py
mpd_now_playable/receivers/websockets/receiver.py
mpd_now_playable/song/__init__.py
mpd_now_playable/song/artwork.py
mpd_now_playable/song/musicbrainz.py
mpd_now_playable/song/song.py
mpd_now_playable/song/stopped.py
mpd_now_playable-1.5.4.dist-info/RECORD
