Metadata-Version: 2.1
Name: mpd-now-playable
Version: 1.5.4
Summary: Expose your MPD server as a 'now playable' app on MacOS
Author-Email: Danielle McLean <dani@00dani.me>
License: MIT
Classifier: Environment :: No Input/Output (Daemon)
Classifier: License :: OSI Approved :: MIT License
Classifier: Operating System :: MacOS :: MacOS X
Classifier: Programming Language :: Python :: 3.12
Classifier: Topic :: Multimedia :: Sound/Audio :: Players
Project-URL: Homepage, https://git.00dani.me/00dani/mpd-now-playable
Project-URL: Issues, https://git.00dani.me/00dani/mpd-now-playable/issues
Requires-Python: >=3.12
Requires-Dist: aiocache>=0.12.2
Requires-Dist: pyobjc-framework-MediaPlayer>=10.0; sys_platform == "darwin"
Requires-Dist: python-mpd2>=3.1.0
Requires-Dist: xdg-base-dirs>=6.0.1
Requires-Dist: pytomlpp>=1.0.13
Requires-Dist: yarl>=1.9.4
Requires-Dist: boltons>=24.0.0
Requires-Dist: pydantic>=2.7.4
Requires-Dist: rich>=13.7.1
Requires-Dist: ormsgpack>=1.5.0
Provides-Extra: redis
Requires-Dist: aiocache[redis]; extra == "redis"
Provides-Extra: memcached
Requires-Dist: aiocache[memcached]; extra == "memcached"
Provides-Extra: websockets
Requires-Dist: websockets>=12.0; extra == "websockets"
Provides-Extra: all
Requires-Dist: mpd-now-playable[memcached,redis,websockets]; extra == "all"
